Metadata-Version: 1.0
Name: Shreck
Version: 0.0
Summary: I cant describe it...
Home-page: UNKNOWN
Author: UNKNOWN
Author-email: pablopris2000zzz@gmail.com
License: UNKNOWN
Platform: UNKNOWN
